qiskit/VERSION.txt
qiskit/__init__.py
qiskit/_accelerate.abi3.so
qiskit/_numpy_compat.py
qiskit/exceptions.py
qiskit/user_config.py
qiskit/version.py
qiskit/circuit/__init__.py
qiskit/circuit/_add_control.py
qiskit/circuit/_classical_resource_map.py
qiskit/circuit/_standard_gates_commutations.py
qiskit/circuit/_utils.py
qiskit/circuit/annotated_operation.py
qiskit/circuit/annotation.py
qiskit/circuit/barrier.py
qiskit/circuit/commutation_checker.py
qiskit/circuit/commutation_library.py
qiskit/circuit/controlledgate.py
qiskit/circuit/delay.py
qiskit/circuit/duration.py
qiskit/circuit/equivalence.py
qiskit/circuit/equivalence_library.py
qiskit/circuit/exceptions.py
qiskit/circuit/gate.py
qiskit/circuit/instruction.py
qiskit/circuit/instructionset.py
qiskit/circuit/measure.py
qiskit/circuit/operation.py
qiskit/circuit/parameter.py
qiskit/circuit/parameterexpression.py
qiskit/circuit/parametertable.py
qiskit/circuit/parametervector.py
qiskit/circuit/quantumcircuit.py
qiskit/circuit/quantumcircuitdata.py
qiskit/circuit/reset.py
qiskit/circuit/singleton.py
qiskit/circuit/store.py
qiskit/circuit/twirling.py
qiskit/circuit/classical/__init__.py
qiskit/circuit/classical/expr/__init__.py
qiskit/circuit/classical/expr/constructors.py
qiskit/circuit/classical/expr/expr.py
qiskit/circuit/classical/expr/visitors.py
qiskit/circuit/classical/types/__init__.py
qiskit/circuit/classical/types/ordering.py
qiskit/circuit/classical/types/types.py
qiskit/circuit/controlflow/__init__.py
qiskit/circuit/controlflow/_builder_utils.py
qiskit/circuit/controlflow/box.py
qiskit/circuit/controlflow/break_loop.py
qiskit/circuit/controlflow/builder.py
qiskit/circuit/controlflow/continue_loop.py
qiskit/circuit/controlflow/control_flow.py
qiskit/circuit/controlflow/for_loop.py
qiskit/circuit/controlflow/if_else.py
qiskit/circuit/controlflow/switch_case.py
qiskit/circuit/controlflow/while_loop.py
qiskit/circuit/library/__init__.py
qiskit-2.3.0.dist-info/METADATA
qiskit-2.3.0.dist-info/WHEEL
qiskit-2.3.0.dist-info/entry_points.txt
qiskit-2.3.0.dist-info/top_level.txt
qiskit-2.3.0.dist-info/RECORD
qiskit-2.3.0.dist-info/licenses/LICENSE.txt
