Metadata-Version: 2.4
Name: qiskit
Version: 2.3.0
Summary: An open-source SDK for working with quantum computers at the level of extended quantum circuits, operators, and primitives.
Author-email: Qiskit Development Team <qiskit@us.ibm.com>
License-Expression: Apache-2.0
Project-URL: Homepage, https://www.ibm.com/quantum/qiskit
Project-URL: Documentation, https://quantum.cloud.ibm.com/docs
Project-URL: API Reference, https://quantum.cloud.ibm.com/docs/api/qiskit
Project-URL: Repository, https://github.com/Qiskit/qiskit
Project-URL: Issues, https://github.com/Qiskit/qiskit/issues
Project-URL: Changelog, https://quantum.cloud.ibm.com/docs/api/qiskit/release-notes
Keywords: qiskit,quantum circuit,quantum computing,quantum programming language,quantum,sdk
Classifier: Environment :: Console
Classifier: Intended Audience :: Developers
Classifier: Intended Audience :: Science/Research
Classifier: Operating System :: MacOS
Classifier: Operating System :: Microsoft :: Windows
Classifier: Operating System :: POSIX :: Linux
Classifier: Programming Language :: Python :: 3 :: Only
Classifier: Programming Language :: Python :: 3.10
Classifier: Programming Language :: Python :: 3.11
Classifier: Programming Language :: Python :: 3.12
Classifier: Programming Language :: Python :: 3.13
Classifier: Topic :: Scientific/Engineering
Requires-Python: >=3.10
License-File: LICENSE.txt
Requires-Dist: rustworkx>=0.15.0
Requires-Dist: numpy<3,>=1.17
Requires-Dist: scipy>=1.5
Requires-Dist: dill>=0.3
Requires-Dist: stevedore>=3.0.0
Requires-Dist: typing-extensions
Provides-Extra: qasm3-import
Requires-Dist: qiskit-qasm3-import>=0.1.0; extra == "qasm3-import"
Provides-Extra: visualization
Requires-Dist: matplotlib>=3.3; extra == "visualization"
Requires-Dist: pydot; extra == "visualization"
Requires-Dist: Pillow>=4.2.1; extra == "visualization"
Requires-Dist: pylatexenc>=1.4; extra == "visualization"
Requires-Dist: seaborn>=0.9.0; extra == "visualization"
Requires-Dist: sympy>=1.3; extra == "visualization"
Provides-Extra: crosstalk-pass
Requires-Dist: z3-solver>=4.7; extra == "crosstalk-pass"
Provides-Extra: csp-layout-pass
Requires-Dist: python-constraint>=1.4; extra == "csp-layout-pass"
Provides-Extra: qpy-compat
Requires-Dist: symengine<0.14,>=0.11; extra == "qpy-compat"
Requires-Dist: sympy>1.3; extra == "qpy-compat"
Provides-Extra: all
Requires-Dist: qiskit[crosstalk-pass,csp-layout-pass,qasm3-import,qpy-compat,visualization]; extra == "all"
Dynamic: license-file
